<?xml version="1.0" encoding="UTF-8"?>
<Defs>

  <SoundDef>
    <defName>USH_ElectricSpark</defName>
    <context>MapOnly</context>
    <maxSimultaneous>1</maxSimultaneous>
    <subSounds>
      <li>
        <grains>
          <li Class="AudioGrain_Clip">
            <clipPath>Misc/ElectricSpark</clipPath>
          </li>
        </grains>
        <volumeRange>15~20.43478</volumeRange>
        <pitchRange>0.9152174~1.042391</pitchRange>
      </li>
    </subSounds>
  </SoundDef>

  <SoundDef>
    <defName>USH_Desensitize</defName>
    <context>MapOnly</context>
    <maxSimultaneous>1</maxSimultaneous>
    <subSounds>
      <li>
        <grains>
          <li Class="AudioGrain_Clip">
            <clipPath>Misc/Desensitize</clipPath>
          </li>
        </grains>
        <volumeRange>8</volumeRange>
        <pitchRange>0.9152174~1.042391</pitchRange>
      </li>
    </subSounds>
  </SoundDef>

  <SoundDef>
    <defName>USH_WallRaise</defName>
    <context>MapOnly</context>
    <maxSimultaneous>3</maxSimultaneous>
    <subSounds>
      <li>
        <grains>
          <li Class="AudioGrain_Clip">
            <clipPath>Misc/WallRaise</clipPath>
          </li>
        </grains>
        <volumeRange>18~23</volumeRange>
        <pitchRange>0.9152174~1.042391</pitchRange>
      </li>
    </subSounds>
  </SoundDef>

  <SoundDef>
    <defName>USH_AbsorbMemoryCell</defName>
    <context>MapOnly</context>
    <maxSimultaneous>1</maxSimultaneous>
    <subSounds>
      <li>
        <grains>
          <li Class="AudioGrain_Clip">
            <clipPath>Misc/AbsorbCell</clipPath>
          </li>
        </grains>
        <volumeRange>28</volumeRange>
        <pitchRange>0.8~1.2</pitchRange>
        <distRange>0~51.86047</distRange>
        <sustainLoop>False</sustainLoop>
      </li>
    </subSounds>
  </SoundDef>

  <SoundDef>
    <defName>USH_ExtractMemory</defName>
    <context>MapOnly</context>
    <maxSimultaneous>1</maxSimultaneous>
    <subSounds>
      <li>
        <grains>
          <li Class="AudioGrain_Clip">
            <clipPath>Misc/ExtractMemory</clipPath>
          </li>
        </grains>
        <volumeRange>18</volumeRange>
        <pitchRange>0.8~1.2</pitchRange>
        <distRange>0~51.86047</distRange>
        <sustainLoop>False</sustainLoop>
      </li>
    </subSounds>
  </SoundDef>

  <SoundDef>
    <defName>USH_InsertMemoryCell</defName>
    <context>MapOnly</context>
    <maxSimultaneous>1</maxSimultaneous>
    <subSounds>
      <li>
        <grains>
          <li Class="AudioGrain_Clip">
            <clipPath>Misc/CellInserted</clipPath>
          </li>
        </grains>
        <volumeRange>25</volumeRange>
        <sustainLoop>False</sustainLoop>
        <distRange>15~40</distRange>
      </li>
    </subSounds>
  </SoundDef>

  <SoundDef>
    <defName>USH_Eject</defName>
    <context>MapOnly</context>
    <maxSimultaneous>1</maxSimultaneous>
    <subSounds>
      <li>
        <grains>
          <li Class="AudioGrain_Clip">
            <clipPath>Misc/Eject</clipPath>
          </li>
        </grains>
        <volumeRange>36</volumeRange>
        <sustainLoop>False</sustainLoop>
        <distRange>15~40</distRange>
      </li>
    </subSounds>
  </SoundDef>

  <SoundDef>
    <defName>USH_GlittershipStopped</defName>
    <context>MapOnly</context>
    <maxSimultaneous>1</maxSimultaneous>
    <subSounds>
      <li>
        <grains>
          <li Class="AudioGrain_Clip">
            <clipPath>Misc/GlittershipStopped</clipPath>
          </li>
        </grains>
        <volumeRange>20</volumeRange>
        <sustainLoop>False</sustainLoop>
        <distRange>15~40</distRange>
      </li>
    </subSounds>
  </SoundDef>

  <SoundDef>
    <defName>USH_GlittershipAmbience</defName>
    <sustain>True</sustain>
    <context>MapOnly</context>
    <priorityMode>PrioritizeNearest</priorityMode>
    <maxSimultaneous>1</maxSimultaneous>
    <maxVoices>1</maxVoices>
    <subSounds>
      <li>
        <muteWhenPaused>True</muteWhenPaused>
        <grains>
          <li Class="AudioGrain_Clip">
            <clipPath>Misc/GlittershipAmbience</clipPath>
          </li>
        </grains>
        <volumeRange>28</volumeRange>
        <distRange>15~40</distRange>
      </li>
    </subSounds>
  </SoundDef>


</Defs>